decode/__init__.py
decode/decode.py
decode/skeleton.py
DEC_Tec_decode-0.0.3.dist-info/LICENSE.txt
DEC_Tec_decode-0.0.3.dist-info/METADATA
DEC_Tec_decode-0.0.3.dist-info/WHEEL
DEC_Tec_decode-0.0.3.dist-info/entry_points.txt
DEC_Tec_decode-0.0.3.dist-info/top_level.txt
DEC_Tec_decode-0.0.3.dist-info/RECORD
