Metadata-Version: 2.1
Name: DEC-Tec-decode
Version: 0.0.3
Summary: Decodes DEC-Tec sequences based on a provided ID.
Home-page: https://github.com/pyscaffold/pyscaffold/
Author: FEI YUAN
Author-email: fei.yuan@bcm.edu
License: MIT
Project-URL: Documentation, https://pyscaffold.org/
Platform: any
Classifier: Development Status :: 4 - Beta
Classifier: Programming Language :: Python
License-File: LICENSE.txt
Requires-Dist: cmder
Requires-Dist: importlib-metadata ; python_version >= "3.8"
Provides-Extra: testing
Requires-Dist: setuptools ; extra == 'testing'
Requires-Dist: pytest ; extra == 'testing'
Requires-Dist: pytest-cov ; extra == 'testing'
